pysperf/__init__.py
pysperf/__main__.py
pysperf/analysis.py
pysperf/base_classes.py
pysperf/config.py
pysperf/model_library.py
pysperf/model_library_registration.py
pysperf/model_types.py
pysperf/pysperf_job_runner.py
pysperf/run_manager.py
pysperf/serial_run_manager.py
pysperf/solver_library.py
pysperf/solver_library_tools.py
pysperf/torque_run_manager.py
pysperf/models/__init__.py
pysperf/models/gdplib.py
pysperf/models/minlplib.py
pysperf/models/private_models.py
pysperf/models/pyomo_examples.py
pysperf/solvers/__init__.py
pysperf/solvers/gams_minlp.py
pysperf/solvers/gdpopt.py
pysperf/solvers/mindtpy.py
pysperf-20.6.3.post1.dist-info/LICENSE
pysperf-20.6.3.post1.dist-info/METADATA
pysperf-20.6.3.post1.dist-info/WHEEL
pysperf-20.6.3.post1.dist-info/entry_points.txt
pysperf-20.6.3.post1.dist-info/top_level.txt
pysperf-20.6.3.post1.dist-info/RECORD
